{"annotation": {"folder": "images", "filename": "maksssksksss184.png", "size": {"width": "400", "height": "220", "depth": "3"}, "segmented": "0", "object": [{"name": "with_mask", "pose": "Unspecified", "truncated": "0", "occluded": "0", "difficult": "0", "bndbox": {"xmin": "143", "ymin": "44", "xmax": "169", "ymax": "73"}}, {"name": "with_mask", "pose": "Unspecified", "truncated": "0", "occluded": "0", "difficult": "0", "bndbox": {"xmin": "171", "ymin": "37", "xmax": "195", "ymax": "65"}}, {"name": "with_mask", "pose": "Unspecified", "truncated": "0", "occluded": "0", "difficult": "0", "bndbox": {"xmin": "250", "ymin": "25", "xmax": "274", "ymax": "46"}}, {"name": "with_mask", "pose": "Unspecified", "truncated": "0", "occluded": "0", "difficult": "0", "bndbox": {"xmin": "256", "ymin": "49", "xmax": "283", "ymax": "76"}}, {"name": "with_mask", "pose": "Unspecified", "truncated": "0", "occluded": "0", "difficult": "0", "bndbox": {"xmin": "262", "ymin": "116", "xmax": "294", "ymax": "145"}}, {"name": "with_mask", "pose": "Unspecified", "truncated": "0", "occluded": "0", "difficult": "0", "bndbox": {"xmin": "294", "ymin": "43", "xmax": "316", "ymax": "63"}}, {"name": "with_mask", "pose": "Unspecified", "truncated": "0", "occluded": "0", "difficult": "0", "bndbox": {"xmin": "334", "ymin": "38", "xmax": "350", "ymax": "57"}}, {"name": "with_mask", "pose": "Unspecified", "truncated": "0", "occluded": "0", "difficult": "0", "bndbox": {"xmin": "320", "ymin": "40", "xmax": "335", "ymax": "57"}}, {"name": "with_mask", "pose": "Unspecified", "truncated": "0", "occluded": "0", "difficult": "0", "bndbox": {"xmin": "374", "ymin": "47", "xmax": "386", "ymax": "61"}}, {"name": "with_mask", "pose": "Unspecified", "truncated": "0", "occluded": "0", "difficult": "0", "bndbox": {"xmin": "83", "ymin": "11", "xmax": "109", "ymax": "49"}}]}}