{"annotation": {"folder": "images", "filename": "maksssksksss575.png", "size": {"width": "400", "height": "225", "depth": "3"}, "segmented": "0", "object": [{"name": "with_mask", "pose": "Unspecified", "truncated": "0", "occluded": "0", "difficult": "0", "bndbox": {"xmin": "170", "ymin": "43", "xmax": "195", "ymax": "69"}}, {"name": "without_mask", "pose": "Unspecified", "truncated": "0", "occluded": "0", "difficult": "0", "bndbox": {"xmin": "36", "ymin": "99", "xmax": "54", "ymax": "114"}}, {"name": "without_mask", "pose": "Unspecified", "truncated": "0", "occluded": "0", "difficult": "0", "bndbox": {"xmin": "234", "ymin": "153", "xmax": "258", "ymax": "186"}}, {"name": "without_mask", "pose": "Unspecified", "truncated": "0", "occluded": "0", "difficult": "0", "bndbox": {"xmin": "383", "ymin": "127", "xmax": "400", "ymax": "150"}}, {"name": "without_mask", "pose": "Unspecified", "truncated": "0", "occluded": "0", "difficult": "0", "bndbox": {"xmin": "220", "ymin": "86", "xmax": "230", "ymax": "102"}}]}}