{"annotation": {"folder": "images", "filename": "maksssksksss64.png", "size": {"width": "400", "height": "225", "depth": "3"}, "segmented": "0", "object": [{"name": "with_mask", "pose": "Unspecified", "truncated": "0", "occluded": "0", "difficult": "0", "bndbox": {"xmin": "99", "ymin": "44", "xmax": "116", "ymax": "64"}}, {"name": "with_mask", "pose": "Unspecified", "truncated": "0", "occluded": "0", "difficult": "0", "bndbox": {"xmin": "151", "ymin": "41", "xmax": "171", "ymax": "61"}}, {"name": "with_mask", "pose": "Unspecified", "truncated": "0", "occluded": "0", "difficult": "0", "bndbox": {"xmin": "306", "ymin": "21", "xmax": "326", "ymax": "42"}}, {"name": "with_mask", "pose": "Unspecified", "truncated": "0", "occluded": "0", "difficult": "0", "bndbox": {"xmin": "354", "ymin": "32", "xmax": "357", "ymax": "38"}}, {"name": "without_mask", "pose": "Unspecified", "truncated": "0", "occluded": "0", "difficult": "0", "bndbox": {"xmin": "275", "ymin": "32", "xmax": "277", "ymax": "35"}}, {"name": "with_mask", "pose": "Unspecified", "truncated": "0", "occluded": "0", "difficult": "0", "bndbox": {"xmin": "243", "ymin": "34", "xmax": "246", "ymax": "37"}}, {"name": "with_mask", "pose": "Unspecified", "truncated": "0", "occluded": "0", "difficult": "0", "bndbox": {"xmin": "207", "ymin": "38", "xmax": "208", "ymax": "40"}}, {"name": "with_mask", "pose": "Unspecified", "truncated": "0", "occluded": "0", "difficult": "0", "bndbox": {"xmin": "216", "ymin": "37", "xmax": "218", "ymax": "39"}}, {"name": "with_mask", "pose": "Unspecified", "truncated": "0", "occluded": "0", "difficult": "0", "bndbox": {"xmin": "217", "ymin": "36", "xmax": "219", "ymax": "39"}}, {"name": "with_mask", "pose": "Unspecified", "truncated": "0", "occluded": "0", "difficult": "0", "bndbox": {"xmin": "226", "ymin": "35", "xmax": "227", "ymax": "37"}}, {"name": "with_mask", "pose": "Unspecified", "truncated": "0", "occluded": "0", "difficult": "0", "bndbox": {"xmin": "230", "ymin": "36", "xmax": "231", "ymax": "38"}}]}}